package_name/__init__.py
swear-3.14159.dist-info/METADATA
swear-3.14159.dist-info/WHEEL
swear-3.14159.dist-info/top_level.txt
swear-3.14159.dist-info/RECORD
